racs/__init__.py
racs/racs.py
racs/racs_exceptions.py
racs/tests/__init__.py
racs/tests/test_racs.py
racs_py_lib-0.1.7.dist-info/METADATA
racs_py_lib-0.1.7.dist-info/WHEEL
racs_py_lib-0.1.7.dist-info/top_level.txt
racs_py_lib-0.1.7.dist-info/RECORD
