Metadata-Version: 2.1
Name: racs-py-lib
Version: 0.1.7
Author: miilkaa
Requires-Dist: requests
